[
  {
    "slug": "entry456",
    "title": "【Twitter】高度な検索/検索コマンドが超便利！",
    "lastUpdate": "2022-04-15",
    "count": 2,
    "dueDate": "2022-07-15",
    "overdueDays": 1351,
    "seo": [
      {
        "query": "twitter 高度な検索 アプリ",
        "imp": 64,
        "pos": 34.22,
        "clk": 0
      },
      {
        "query": "twitter 高度な検索",
        "imp": 33,
        "pos": 40.97,
        "clk": 0
      },
      {
        "query": "めっちゃ高度な検索",
        "imp": 22,
        "pos": 8.05,
        "clk": 0
      },
      {
        "query": "min retweet",
        "imp": 21,
        "pos": 10.38,
        "clk": 0
      },
      {
        "query": "高度な検索",
        "imp": 15,
        "pos": 46.6,
        "clk": 0
      },
      {
        "query": "twitter 検索コマンド",
        "imp": 14,
        "pos": 58.79,
        "clk": 0
      },
      {
        "query": "ツイッター高度な検索",
        "imp": 9,
        "pos": 48.56,
        "clk": 0
      },
      {
        "query": "高度な検索 twitter",
        "imp": 6,
        "pos": 27.5,
        "clk": 0
      },
      {
        "query": "twitter コマンド",
        "imp": 6,
        "pos": 67.5,
        "clk": 0
      },
      {
        "query": "twitter 検索 コマンド",
        "imp": 6,
        "pos": 66.17,
        "clk": 0
      }
    ]
  },
  {
    "slug": "entry447",
    "title": "職業訓練校のプログラミング学習で就職できる？事例&評判をご紹介",
    "lastUpdate": "2023-03-14",
    "count": 2,
    "dueDate": "2023-06-14",
    "overdueDays": 1017,
    "seo": [
      {
        "query": "職業訓練校 プログラミング",
        "imp": 17,
        "pos": 14.35,
        "clk": 0
      },
      {
        "query": "職業訓練 プログラミング",
        "imp": 16,
        "pos": 14.13,
        "clk": 0
      },
      {
        "query": "職業訓練校プログラミング",
        "imp": 16,
        "pos": 35.13,
        "clk": 0
      },
      {
        "query": "職業訓練 プログラミング 無駄",
        "imp": 12,
        "pos": 47.58,
        "clk": 0
      },
      {
        "query": "プログラミング 職業訓練",
        "imp": 10,
        "pos": 24.7,
        "clk": 0
      },
      {
        "query": "職業訓練校プログラミングスクール",
        "imp": 10,
        "pos": 18,
        "clk": 0
      },
      {
        "query": "ハローワーク プログラミング 職業訓練",
        "imp": 9,
        "pos": 1,
        "clk": 0
      },
      {
        "query": "職業 訓練 プログラミング",
        "imp": 8,
        "pos": 37.5,
        "clk": 0
      },
      {
        "query": "職業 訓練校 プログラミングスクール",
        "imp": 8,
        "pos": 21.5,
        "clk": 0
      },
      {
        "query": "プログラミングスクール 就職 できない",
        "imp": 6,
        "pos": 80.83,
        "clk": 0
      }
    ]
  }
]