{"data":{"allMarkdownRemark":{"totalCount":6,"edges":[{"node":{"fields":{"slug":"/blogs/entry453/"},"frontmatter":{"title":"憧れの海外ノマドワーカー。未経験でもエンジニアでもなれるの？","date":"2021.04.09","hero":"2021/entry453.jpg","tags":["駆け出しエンジニア","フリーランス"]}}},{"node":{"fields":{"slug":"/blogs/entry417/"},"frontmatter":{"title":"海外は治安が悪い？！住む場所を選んで上手に海外生活する方法","date":"2020.12.15","hero":"2020/entry417.jpg","tags":["セブ島エンジニア生活","海外移住","フリーランス"]}}},{"node":{"fields":{"slug":"/blogs/entry415/"},"frontmatter":{"title":"2021年セブ島にオフショア会社設立。かみーゆ、YouTubeはじめました","date":"2020.12.13","hero":"2020/entry415.jpg","tags":["キャリアアップ・転職","フリーランス","海外移住"]}}},{"node":{"fields":{"slug":"/blogs/entry414/"},"frontmatter":{"title":"ベンチャーはやめとくべき？5社経験した私が事実を語ります","date":"2020.12.10","hero":"2020/entry414.jpg","tags":["キャリアアップ・転職","フリーランス"]}}},{"node":{"fields":{"slug":"/blogs/entry397/"},"frontmatter":{"title":"2021年無くなったら社畜が幸せになりそうなこと7コ","date":"2020.11.15","hero":"2020/entry397.jpg","tags":["キャリアアップ・転職","フリーランス"]}}},{"node":{"fields":{"slug":"/blogs/entry377/"},"frontmatter":{"title":"フリーランス経験から学ぶ副業のススメ","date":"2020.07.25","hero":"2020/entry377.jpg","tags":["駆け出しエンジニア","キャリアアップ・転職","フリーランス"]}}}]}},"pageContext":{"limit":12,"skip":0,"current":1,"page":1,"tag":"フリーランス"}}